secretflow_spec/__init__.py
secretflow_spec/version.py
secretflow_spec/core/__init__.py
secretflow_spec/core/component.py
secretflow_spec/core/definition.py
secretflow_spec/core/discovery.py
secretflow_spec/core/registry.py
secretflow_spec/core/types.py
secretflow_spec/core/utils.py
secretflow_spec/core/version.py
secretflow_spec/core/dist_data/__init__.py
secretflow_spec/core/dist_data/base.py
secretflow_spec/core/dist_data/file.py
secretflow_spec/core/dist_data/report.py
secretflow_spec/core/dist_data/vtable.py
secretflow_spec/core/storage/__init__.py
secretflow_spec/core/storage/base.py
secretflow_spec/core/storage/local.py
secretflow_spec/core/storage/s3.py
secretflow_spec/v1/__init__.py
secretflow_spec/v1/component_pb2.py
secretflow_spec/v1/component_pb2.pyi
secretflow_spec/v1/data_pb2.py
secretflow_spec/v1/data_pb2.pyi
secretflow_spec/v1/evaluation_pb2.py
secretflow_spec/v1/evaluation_pb2.pyi
secretflow_spec/v1/report_pb2.py
secretflow_spec/v1/report_pb2.pyi
tests/__init__.py
tests/test_definition.py
tests/test_discovery.py
tests/test_dist_data.py
tests/test_registry.py
tests/test_storage.py
tests/test_utils.py
tests/comps/__init__.py
tests/comps/my_comp.py
secretflow_spec-1.1.0b0.dist-info/LICENSE
secretflow_spec-1.1.0b0.dist-info/METADATA
secretflow_spec-1.1.0b0.dist-info/WHEEL
secretflow_spec-1.1.0b0.dist-info/top_level.txt
secretflow_spec-1.1.0b0.dist-info/RECORD
